LICENSE
MANIFEST.in
setup.cfg
setup.py
django_adv_imagefield.egg-info/PKG-INFO
django_adv_imagefield.egg-info/SOURCES.txt
django_adv_imagefield.egg-info/dependency_links.txt
django_adv_imagefield.egg-info/requires.txt
django_adv_imagefield.egg-info/top_level.txt
media_field/__init__.py
media_field/admin.py
media_field/api.py
media_field/db.py
media_field/forms.py
media_field/views.py
media_field/static/media_field/mediaField.js
media_field/static/media_field/media_field.css
media_field/tests/__init__.py
media_field/tests/__init__.pyc
media_field/tests/test_field.pyc
media_field/tests/test_forms.py
media_field/tests/test_forms.pyc
media_field/tests/test_models.py
media_field/tests/test_models.pyc