Metadata-Version: 1.1
Name: django-adv-imagefield
Version: 0.0.3
Summary: Advanced ImageField for Django that provides widget to search Flickr and Google Images
Home-page: https://github.com/devangmundhra/django-adv-imagefield
Author: Devang Mundhra
Author-email: devangmundhra@gmail.com
License: MIT
Keywords: django,imagefield,media,flickr,google-image-search
Platform: UNKNOWN
Classifier: Development Status :: 4 - Beta
Classifier: Environment :: Web Environment
Classifier: Framework :: Django
Classifier: Intended Audience :: Developers
Classifier: License :: OSI Approved :: MIT License
Classifier: Operating System :: OS Independent
Classifier: Programming Language :: Python
Classifier: Programming Language :: Python :: 2
Classifier: Programming Language :: Python :: 3
Classifier: Topic :: Utilities
